converter/__init__.py
converter/__main__.py
converter/cli.py
converter/core.py
converter/renderers.py
zone3k_csv_converter-0.9.2.dist-info/METADATA
zone3k_csv_converter-0.9.2.dist-info/WHEEL
zone3k_csv_converter-0.9.2.dist-info/entry_points.txt
zone3k_csv_converter-0.9.2.dist-info/top_level.txt
zone3k_csv_converter-0.9.2.dist-info/RECORD
